[
    {
        "id": 101,
        "url": "../../assets/videos/MSD knock.mp4",
        "desc": " MS.Dhoni Stunning knock Against ENG",
        "Director": " Against England",
        "Music": "WHen team needs He is here like a Roaring Lion",
        "no.ofBalls": "no.og balls he fased",
        "Singer": "56 of 26 balls"
    },
    {
        "id": 102,
        "url": "../../assets/videos/Shivuni_SOng_Bahubali.mp4",
        "desc": " Baahubali Sivuni Aana song",
        "Director": " Director : S.S.Rajamouli",
        "Movie": "Baahubali",
        "Music": "Music By : M.M.Keeravaani",
        "Singer": "Vocals:M.M.Keeravaani @ Monima",
        "Lyricist": "  Inaganti Sunar"
    },
    {
        "id": 103,
        "url": "../../assets/videos/Bhuvi_Remove_EveryOne.mp4",
        "desc": "Bhuvaneswal Kumar on fire",
        "Director": " Against England",
        "no.ofWickets": 6,
        "Music": "First time in his carreer",
        "Singer": "6/80(25)"
    },
    {
        "id": 104,
        "url": "../../assets/videos/Nippule_Swasaga_Bahubali.mp4",
        "desc": " Baahubali Sivuni Aana song",
        "Director": " Director : S.S.Rajamouli",
        "Movie": "Baahubali",
        "Music": " Music By :M.M.Keeravaani",
        "Singer": "Vocal :M.M.Keeravaani",
        "Lyricist": "  Inaganti Sunar @ K. Shiva Shakthi"
    },
    {
        "id": 105,
        "url": "../../assets/videos/MSD knock.mp4",
        "desc": " MS.Dhoni Stunning knock Against ENG",
        "Director": " Against England",
        "Music": "WHen team needs He is here like a Roaring Lion",
        "no.ofBalls": "no.og balls he fased",
        "Singer": "56 of 26 balls"
    },
    {
        "id": 106,
        "url": "../../assets/videos/Shivuni_SOng_Bahubali.mp4",
        "desc": " Baahubali Sivuni Aana song",
        "Director": " Director : S.S.Rajamouli",
        "Movie": "Baahubali",
        "Music": "Music By : M.M.Keeravaani",
        "Singer": "Vocals:M.M.Keeravaani @ Monima",
        "Lyricist": "  Inaganti Sunar"
    }
]